README.rst
setup.py
metriquet/__init__.py
metriquet/tornadohttp.py
metriquet.egg-info/PKG-INFO
metriquet.egg-info/SOURCES.txt
metriquet.egg-info/dependency_links.txt
metriquet.egg-info/requires.txt
metriquet.egg-info/top_level.txt